cap/__init__.py
cap/actions.py
cap/decorators.py
cap/filters.py
cap/menu.py
cap/translation.py
cap/views.py
cap/widgets.py
cap/locale/uk/LC_MESSAGES/django.mo
cap/locale/uk/LC_MESSAGES/django.po
cap/static/cap/components/jquery.cookie.js
cap/static/cap/components/jquery.form.min.js
cap/static/cap/components/jquery.min.js
cap/static/cap/components/bootstrap/bootstrap.bundle.min.js
cap/static/cap/components/bootstrap/bootstrap.min.css
cap/static/cap/components/bootstrap-tagsinput/bootstrap-tagsinput.css
cap/static/cap/components/bootstrap-tagsinput/bootstrap-tagsinput.js
cap/static/cap/components/bootstrap-treeview/bootstrap-treeview.min.css
cap/static/cap/components/bootstrap-treeview/bootstrap-treeview.min.js
cap/static/cap/components/fancybox/jquery.fancybox.min.css
cap/static/cap/components/fancybox/jquery.fancybox.min.js
cap/static/cap/components/font-awesome/font-awesome.min.css
cap/static/cap/components/font-awesome/fonts/FontAwesome.otf
cap/static/cap/components/font-awesome/fonts/fontawesome-webfont.eot
cap/static/cap/components/font-awesome/fonts/fontawesome-webfont.svg
cap/static/cap/components/font-awesome/fonts/fontawesome-webfont.ttf
cap/static/cap/components/font-awesome/fonts/fontawesome-webfont.woff
cap/static/cap/components/font-awesome/fonts/fontawesome-webfont.woff2
cap/static/cap/components/jquery-ui/jquery-ui.min.css
cap/static/cap/components/jquery-ui/jquery-ui.min.js
cap/static/cap/components/jquery-ui/i18n/en.js
cap/static/cap/components/jquery-ui/i18n/ru.js
cap/static/cap/components/jquery-ui/i18n/uk.js
cap/static/cap/components/jquery-ui/images/ui-bg_flat_0_aaaaaa_40x100.png
cap/static/cap/components/jquery-ui/images/ui-icons_444444_256x240.png
cap/static/cap/components/jquery-ui/images/ui-icons_555555_256x240.png
cap/static/cap/components/jquery-ui/images/ui-icons_777620_256x240.png
cap/static/cap/components/jquery-ui/images/ui-icons_777777_256x240.png
cap/static/cap/components/jquery-ui/images/ui-icons_cc0000_256x240.png
django_mp_cap-4.0.3.dist-info/licenses/LICENSE
django_mp_cap-4.0.3.dist-info/METADATA
django_mp_cap-4.0.3.dist-info/WHEEL
django_mp_cap-4.0.3.dist-info/top_level.txt
django_mp_cap-4.0.3.dist-info/RECORD
