Metadata-Version: 2.4
Name: django-mp-cap
Version: 4.0.3
Summary: Django admin app
Home-page: https://github.com/pmaigutyak/mp-cap
Download-URL: https://github.com/pmaigutyak/mp-cap/archive/4.0.3.tar.gz
Author: Paul Maigutyak
Author-email: pmaigutyak@gmail.com
License: MIT
License-File: LICENSE
Dynamic: author
Dynamic: author-email
Dynamic: download-url
Dynamic: home-page
Dynamic: license
Dynamic: license-file
Dynamic: summary
